singer/__init__.py
singer/bookmarks.py
singer/catalog.py
singer/logger.py
singer/logging.conf
singer/messages.py
singer/metadata.py
singer/metrics.py
singer/requests.py
singer/schema.py
singer/statediff.py
singer/transform.py
singer/utils.py
realit_singer_python-5.0.3.dist-info/LICENSE
realit_singer_python-5.0.3.dist-info/METADATA
realit_singer_python-5.0.3.dist-info/WHEEL
realit_singer_python-5.0.3.dist-info/entry_points.txt
realit_singer_python-5.0.3.dist-info/RECORD
