Metadata-Version: 2.1
Name: realit-singer-python
Version: 5.0.3
Summary: Singer.io utility library - PipelineWise and Meltano compatible
Home-page: https://github.com/s7clarke10/realit-singer-python
License: Apache 2.0
Keywords: singer,meltano,pipelinewise,framework
Requires-Python: >=3.8,<3.13
Classifier: Development Status :: 5 - Production/Stable
Classifier: License :: OSI Approved :: Apache Software License
Classifier: License :: Other/Proprietary License
Classifier: Programming Language :: Python :: 3
Classifier: Programming Language :: Python :: 3.8
Classifier: Programming Language :: Python :: 3.9
Classifier: Programming Language :: Python :: 3.10
Classifier: Programming Language :: Python :: 3.11
Classifier: Programming Language :: Python :: 3.12
Classifier: Topic :: Database
Requires-Dist: backoff (==2.2.1)
Requires-Dist: ciso8601 (>=2.3.1,<3.0.0)
Requires-Dist: jsonschema (>=4.23.0,<5.0.0)
Requires-Dist: msgspec (>=0.18.0,<0.19.0)
Requires-Dist: python-dateutil (>=2.7.3,<3.0.0)
Requires-Dist: pytz (>=2018.4,<2025.0)
Project-URL: Repository, https://github.com/s7clarke10/realit-singer-python
